django_boolean_sum.py
django_boolean_sum-0.2.dist-info/DESCRIPTION.rst
django_boolean_sum-0.2.dist-info/METADATA
django_boolean_sum-0.2.dist-info/RECORD
django_boolean_sum-0.2.dist-info/WHEEL
django_boolean_sum-0.2.dist-info/metadata.json
django_boolean_sum-0.2.dist-info/top_level.txt
