Metadata-Version: 2.0
Name: django-boolean-sum
Version: 0.2
Summary: UNKNOWN
Home-page: http://incuna.com/
Author: Incuna Ltd.
Author-email: admin@incuna.com
License: UNKNOWN
Platform: UNKNOWN
